BGlib/__init__.py
BGlib/__version__.py
BGlib/be/__init__.py
BGlib/be/analysis/__init__.py
BGlib/be/analysis/be_loop_fitter.py
BGlib/be/analysis/be_relax_fit.py
BGlib/be/analysis/be_sho_fitter.py
BGlib/be/analysis/fitter.py
BGlib/be/analysis/utils/__init__.py
BGlib/be/analysis/utils/be_loop.py
BGlib/be/analysis/utils/be_sho.py
BGlib/be/analysis/utils/tree.py
BGlib/be/translators/__init__.py
BGlib/be/translators/be_odf.py
BGlib/be/translators/be_odf_relaxation.py
BGlib/be/translators/beps_data_generator.py
BGlib/be/translators/beps_ndf.py
BGlib/be/translators/forc_iv.py
BGlib/be/translators/labview_h5_patcher.py
BGlib/be/translators/df_utils/__init__.py
BGlib/be/translators/df_utils/be_utils.py
BGlib/be/translators/df_utils/beps_gen_utils.py
BGlib/be/translators/df_utils/histogram.py
BGlib/be/viz/__init__.py
BGlib/be/viz/be_viz_utils.py
BGlib/be/viz/qt_visualizers/__init__.py
BGlib/be/viz/qt_visualizers/io_funcs.py
BGlib/be/viz/qt_visualizers/plot_functions.py
BGlib/be/viz/qt_visualizers/sho_master.py
BGlib/gmode/__init__.py
BGlib/gmode/analysis/__init__.py
BGlib/gmode/analysis/giv_bayesian.py
BGlib/gmode/analysis/utils/__init__.py
BGlib/gmode/analysis/utils/giv_utils.py
BGlib/gmode/proc/__init__.py
BGlib/gmode/proc/fft.py
BGlib/gmode/proc/gmode_utils.py
BGlib/gmode/proc/hist.py
BGlib/gmode/proc/signal_filter.py
BGlib/gmode/translators/__init__.py
BGlib/gmode/translators/general_dynamic_mode.py
BGlib/gmode/translators/general_mode_vs.py
BGlib/gmode/translators/gmode_iv.py
BGlib/gmode/translators/gmode_line.py
BGlib/gmode/translators/gmode_tune.py
BGlib/gmode/translators/sporc.py
BGlib/gmode/translators/df_utils/__init__.py
BGlib/gmode/translators/df_utils/gmode_utils.py
BGlib/gmode/translators/df_utils/hdf_writer.py
BGlib/gmode/translators/df_utils/virtual_data.py
BGlib/gmode/translators/df_utils/write_utils.py
BGlib/gmode/viz/__init__.py
BGlib/misc/__init__.py
BGlib/misc/translators/__init__.py
BGlib/misc/translators/tr_kpfm.py
BGlib-0.0.5.dist-info/LICENSE
BGlib-0.0.5.dist-info/METADATA
BGlib-0.0.5.dist-info/WHEEL
BGlib-0.0.5.dist-info/top_level.txt
BGlib-0.0.5.dist-info/RECORD
